phanthomos/__init__.py
phanthomos/phatom_data_glover_config.py
phantomos-2.0.dist-info/licenses/LICENSE
phantomos-2.0.dist-info/METADATA
phantomos-2.0.dist-info/WHEEL
phantomos-2.0.dist-info/top_level.txt
phantomos-2.0.dist-info/RECORD
