Metadata-Version: 2.4
Name: phantomos
Version: 2.0
Summary: Build your own virtual drives and drivers for DATAGLOVES to manage PC Visual Systems
Home-page: https://github.com/ssmool/phantom_os
Author: #asytrick
Author-email: eusmool@gmail.com
Classifier: Programming Language :: Python :: 3
Classifier: Operating System :: OS Independent
Requires-Python: >=3.7
License-File: LICENSE
Requires-Dist: opencv-python
Requires-Dist: numpy
Requires-Dist: matplotlib
Requires-Dist: scikit-image
Requires-Dist: webcam
Requires-Dist: keyboard
Requires-Dist: PyAutoGUI
Requires-Dist: pillow
Requires-Dist: lionsmapper
Dynamic: license-file
